MANIFEST.in
README.rst
setup.py
docs/index.rst
docs/package_reference.rst
docs/walkthrough.rst
fouriertransform/__init__.py
fouriertransform/crosstable.py
fouriertransform/crosstable_helper.py
fouriertransform/exceptions.py
fouriertransform/filter_funcs.py
fouriertransform.egg-info/PKG-INFO
fouriertransform.egg-info/SOURCES.txt
fouriertransform.egg-info/dependency_links.txt
fouriertransform.egg-info/not-zip-safe
fouriertransform.egg-info/requires.txt
fouriertransform.egg-info/top_level.txt