Metadata-Version: 1.1
Name: fouriertransform
Version: 0.0.4
Summary: FT-ICR MS peak assignment and data analysis
Home-page: https://github.com/FluvialSeds/fouriertransform
Author: Jordon D. Hemingway
Author-email: jordon_hemingway@fas.harvard.edu
License: GNU GPL Version 3
Download-URL: https://github.com/FluvialSeds/fouriertransform/tarball/0.0.4
Keywords: geochemistry,FT-ICR MS,formula assignment,high-resolution mass spectrometry,carbon cycle
Platform: UNKNOWN
Classifier: Development Status :: 3 - Alpha
Classifier: Intended Audience :: Science/Research
Classifier: License :: Free for non-commercial use
Classifier: Programming Language :: Python
Classifier: Programming Language :: Python :: 3
Classifier: Programming Language :: Python :: 2
Classifier: Programming Language :: Python :: 3.5
Classifier: Programming Language :: Python :: 2.7
Classifier: Topic :: Scientific/Engineering
